AS7343/__init__.py
AS7343/addr.py
AS7343-0.1.1.dist-info/METADATA
AS7343-0.1.1.dist-info/WHEEL
AS7343-0.1.1.dist-info/top_level.txt
AS7343-0.1.1.dist-info/RECORD
