Metadata-Version: 2.1
Name: AS7343
Version: 0.1.1
Summary: AS7343 sensor
Home-page: 
Author: YzxMC
Author-email: yzxuser@gmail.com
Classifier: Programming Language :: Python :: 3
Classifier: License :: OSI Approved :: MIT License
Requires-Python: >=3.5
